flasks_discord/__init__.py
flasks_discord/_http.py
flasks_discord/client.py
flasks_discord/configs.py
flasks_discord/exceptions.py
flasks_discord/utils.py
flasks_discord/models/__init__.py
flasks_discord/models/base.py
flasks_discord/models/connections.py
flasks_discord/models/guild.py
flasks_discord/models/integration.py
flasks_discord/models/user.py
flasks_discord/types/__init__.py
flasks_discord/types/permissions.py
tests/__init__.py
tests/test_app.py
tests/test_factory_app.py
Flasks_Discord-0.1.69.dist-info/LICENSE
Flasks_Discord-0.1.69.dist-info/METADATA
Flasks_Discord-0.1.69.dist-info/WHEEL
Flasks_Discord-0.1.69.dist-info/top_level.txt
Flasks_Discord-0.1.69.dist-info/RECORD
